population_restorator/__init__.py
population_restorator/__main__.py
population_restorator/balancer/__init__.py
population_restorator/balancer/houses.py
population_restorator/balancer/territories.py
population_restorator/click/__init__.py
population_restorator/click/balancer.py
population_restorator/click/divider.py
population_restorator/click/forecaster.py
population_restorator/click/main_group.py
population_restorator/db/__init__.py
population_restorator/db/entities/__init__.py
population_restorator/db/entities/houses_tmp.py
population_restorator/db/entities/population_divided.py
population_restorator/db/entities/social_groups_distribution.py
population_restorator/db/entities/social_groups_probabilities.py
population_restorator/db/ops/__init__.py
population_restorator/db/ops/preparation.py
population_restorator/divider/__init__.py
population_restorator/divider/divide.py
population_restorator/divider/export.py
population_restorator/forecaster/__init__.py
population_restorator/forecaster/ages.py
population_restorator/forecaster/balancing/__init__.py
population_restorator/forecaster/balancing/additional_sgs.py
population_restorator/forecaster/balancing/age_sex.py
population_restorator/forecaster/balancing/primary_sgs.py
population_restorator/forecaster/people.py
population_restorator/models/__init__.py
population_restorator/models/parse/__init__.py
population_restorator/models/parse/social_groups.py
population_restorator/models/parse/survivability_coefficients.py
population_restorator/models/people_division.py
population_restorator/models/sex_age.py
population_restorator/models/social_groups.py
population_restorator/models/survivability_coefficients.py
population_restorator/models/territories.py
population_restorator/utils/__init__.py
population_restorator/utils/data_loader.py
population_restorator/utils/data_saver.py
population_restorator/utils/data_structure.py
population_restorator/utils/dotenv.py
population_restorator-0.2.3.dist-info/entry_points.txt
population_restorator-0.2.3.dist-info/LICENSE
population_restorator-0.2.3.dist-info/METADATA
population_restorator-0.2.3.dist-info/WHEEL
population_restorator-0.2.3.dist-info/RECORD
